Faker_Events-1.6.0.data/scripts/faker-events
faker_events/__init__.py
faker_events/__main__.py
faker_events/events.py
faker_events/example.py
faker_events/handlers.py
faker_events/profiles.py
faker_events/text_color.py
Faker_Events-1.6.0.dist-info/LICENSE
Faker_Events-1.6.0.dist-info/METADATA
Faker_Events-1.6.0.dist-info/WHEEL
Faker_Events-1.6.0.dist-info/top_level.txt
Faker_Events-1.6.0.dist-info/RECORD
