Metadata-Version: 2.1
Name: Faker-Events
Version: 1.6.0
Summary: Generates Events with formatted fake data for streams.
Home-page: https://github.com/johnbrandborg/faker-events
Author: John Brandborg
Author-email: john.brandborg+pypi@pm.me
License: MIT
Project-URL: Source, https://github.com/johnbrandborg/faker-events
Project-URL: Tracker, https://github.com/johnbrandborg/faker-events/issues
Keywords: faker events stream data test generator
Platform: unix
Platform: linux
Platform: osx
Platform: cygwin
Platform: win32
Classifier: Development Status :: 4 - Beta
Classifier: Intended Audience :: Developers
Classifier: License :: OSI Approved :: MIT License
Classifier: Operating System :: MacOS :: MacOS X
Classifier: Operating System :: Microsoft :: Windows
Classifier: Operating System :: POSIX
Classifier: Programming Language :: Python :: 3
Classifier: Programming Language :: Python :: 3 :: Only
Classifier: Programming Language :: Python :: 3.6
Classifier: Programming Language :: Python :: 3.7
Classifier: Programming Language :: Python :: 3.8
Classifier: Programming Language :: Python :: 3.9
Classifier: Programming Language :: Python :: 3.10
Classifier: Topic :: Software Development :: Libraries
Classifier: Topic :: Software Development :: Testing
Classifier: Topic :: Utilities
Requires-Python: >=3.6
License-File: LICENSE
Requires-Dist: faker
Requires-Dist: croniter
Provides-Extra: develop
Requires-Dist: flake8 ; extra == 'develop'
Requires-Dist: pytest ; extra == 'develop'
Requires-Dist: pytest-cov ; extra == 'develop'
Provides-Extra: kafka
Requires-Dist: kafka-python ; extra == 'kafka'
Provides-Extra: kinesis
Requires-Dist: boto3 ; extra == 'kinesis'
